kl_exec_gateway/__init__.py
kl_exec_gateway/chat_session.py
kl_exec_gateway/cli.py
kl_exec_gateway/config_loader.py
kl_exec_gateway/events.py
kl_exec_gateway/kernel_integration.py
kl_exec_gateway/logging_config.py
kl_exec_gateway/models.py
kl_exec_gateway/orchestrator.py
kl_exec_gateway/pipeline_registry.py
kl_exec_gateway/pipeline_types.py
kl_exec_gateway/pipelines.py
kl_exec_gateway/policy.py
kl_exec_gateway/policy_engine.py
kl_exec_gateway/server.py
kl_exec_gateway/session_governance.py
kl_exec_gateway/step_handlers.py
kl_exec_gateway/trace_store.py
kl_exec_gateway/transforms.py
kl_exec_gateway/providers/__init__.py
kl_exec_gateway/providers/openai_client.py
kl_exec_gateway-0.3.1.dist-info/licenses/LICENSE
kl_exec_gateway-0.3.1.dist-info/METADATA
kl_exec_gateway-0.3.1.dist-info/WHEEL
kl_exec_gateway-0.3.1.dist-info/entry_points.txt
kl_exec_gateway-0.3.1.dist-info/top_level.txt
kl_exec_gateway-0.3.1.dist-info/RECORD
