Metadata-Version: 2.4
Name: kl-exec-gateway
Version: 0.3.1
Summary: Execution gateway and policy layer on top of KL Kernel Logic.
Author: Lukas Pfister
License: ﻿MIT License
Requires-Python: >=3.11
License-File: LICENSE
Requires-Dist: typing-extensions>=4.0
Requires-Dist: kl-kernel-logic==0.3.4
Requires-Dist: httpx>=0.28.1
Requires-Dist: fastapi>=0.115.0
Requires-Dist: uvicorn>=0.30.0
Provides-Extra: dev
Requires-Dist: pytest>=8.0; extra == "dev"
Dynamic: license-file
